{
    "message": "찜 목록 리스트 데이터 조회 성공",
    "favorites": [
        {
            "id": 1,
            "festivalTitle": "2024 고려대학교 축제 2024 고려대학교 축제  2024 고려대학교 축제",
            "startDate": "2024-06-30",
            "endDate": "2024-06-30",
            "categories": "대학축제",
            "festivalLocation" : "고려대학교 서울캠퍼스고려대학교 서울캠퍼스고려대학교 서울캠퍼스고려대학교 서울캠퍼스고려대학교 서울캠퍼스고려대학교",
            "posterSrc": "https://mblogthumb-phinf.pstatic.net/MjAyNDA1MjFfMzEg/MDAxNzE2Mjc0NjE5MDAw.xqYwkcFs5a2nOoTlJp8ZpzURbjxqcyI7dVmMQVUxy3sg.IlxyGjArO1FnB7Wn0SkHxP1IWKdGhTQssT90JaVj2PQg.JPEG/KakaoTalk_20240521_155626760.jpg?type=w800"
            
        },
        {
            "id": 2,
            "festivalTitle": "쏜애플 쏜애플 쏜애플 쏜애플 쏜애플 쏜애플 쏜애플 ",
            "startDate": "2024-06-30",
            "endDate": "2024-06-30",
            "categories": "페스티벌",
            "festivalLocation" : "고려대학교 서울캠퍼스",
            "posterSrc": "https://mblogthumb-phinf.pstatic.net/MjAyNDA1MjFfMzEg/MDAxNzE2Mjc0NjE5MDAw.xqYwkcFs5a2nOoTlJp8ZpzURbjxqcyI7dVmMQVUxy3sg.IlxyGjArO1FnB7Wn0SkHxP1IWKdGhTQssT90JaVj2PQg.JPEG/KakaoTalk_20240521_155626760.jpg?type=w800"
        },
        {
            "id": 3,
            "festivalTitle": "2024 서울대학교 축제",
            "startDate": "2024-06-30",
            "endDate": "2024-06-30",
            "categories": "대학축제",
            "festivalLocation" : "고려대학교 서울캠퍼스",
            "posterSrc": "https://mblogthumb-phinf.pstatic.net/MjAyNDA1MjFfMzEg/MDAxNzE2Mjc0NjE5MDAw.xqYwkcFs5a2nOoTlJp8ZpzURbjxqcyI7dVmMQVUxy3sg.IlxyGjArO1FnB7Wn0SkHxP1IWKdGhTQssT90JaVj2PQg.JPEG/KakaoTalk_20240521_155626760.jpg?type=w800"
        }
    ]
}
